__init__.py
samba/SAMBA_metric.py
samba/__init__.py
samba/microbiome2matrix.py
samba/textreeCreate.py
samba_metric-0.0.14.dist-info/METADATA
samba_metric-0.0.14.dist-info/WHEEL
samba_metric-0.0.14.dist-info/top_level.txt
samba_metric-0.0.14.dist-info/RECORD
