Metadata-Version: 2.1
Name: samba_metric
Version: 0.0.14
Author-email: Oshrit Shtossel <oshritvig@gmail.com>
Classifier: License :: OSI Approved :: MIT License
Classifier: Programming Language :: Python
Classifier: Programming Language :: Python :: 3
Requires-Python: >=3.8
Requires-Dist: numpy >=1.19.2
Requires-Dist: pandas >=1.3.4
Requires-Dist: scipy >=1.11.3
Requires-Dist: networkx >=2.5.1
Requires-Dist: tqdm >=4.59.0
Requires-Dist: python-igraph >=0.9.1
Requires-Dist: sewar >=0.4.5
Requires-Dist: umap-learn >=0.5.4
Requires-Dist: matplotlib
Requires-Dist: igraph
Requires-Dist: MIPMLP
